jiggy/__init__.py
jiggy/jiggy_session.py
jiggy/jiggyann.py
jiggy/login.py
jiggy/user.py
jiggy/jiggyboard/__init__.py
jiggy/jiggyboard/artifact_source.py
jiggy/jiggyboard/board.py
jiggy/jiggyboard/jb_wandb.py
jiggy/jiggyboard/jiggy_session.py
jiggy-0.1.9.dist-info/LICENSE
jiggy-0.1.9.dist-info/METADATA
jiggy-0.1.9.dist-info/WHEEL
jiggy-0.1.9.dist-info/top_level.txt
jiggy-0.1.9.dist-info/RECORD
